herptest/__init__.py
herptest/extract_lms_archive.py
herptest/run_test_suite.py
herptest/toolbox.py
herptest-0.9.9.18.dist-info/METADATA
herptest-0.9.9.18.dist-info/WHEEL
herptest-0.9.9.18.dist-info/entry_points.txt
herptest-0.9.9.18.dist-info/top_level.txt
herptest-0.9.9.18.dist-info/RECORD
