Metadata-Version: 2.1
Name: herptest
Version: 0.9.9.18
Summary: Test suite tools for instructors
Home-page: https://github.com/cacticouncil/herptest
Author: Jeremiah Blanchard
Author-email: jjb@eng.ufl.edu
License: GPL 3
Platform: UNKNOWN
Requires-Dist: monkeydict (>=1.0)
Requires-Dist: pathos (>=0.2.7)
Requires-Dist: pexpect (>=4.8.0)
Requires-Dist: pyte (>=0.8.0)
